fuzzing
gp_decorators
