Metadata-Version: 1.1
Name: fuzzing
Version: 0.3.2
Summary: Tools for stress testing applications.
Home-page: https://github.com/stbraun/fuzzing
Author: Stefan Braun
Author-email: sb@action.ms
License: MIT
Keywords: development tools
Platform: UNKNOWN
Classifier: Development Status :: 4 - Beta
Classifier: Intended Audience :: Developers
Classifier: License :: OSI Approved :: MIT License
Classifier: Programming Language :: Python
Classifier: Programming Language :: Python :: 3.3
Classifier: Programming Language :: Python :: 3.4
Classifier: Programming Language :: Python :: 3.5
Classifier: Programming Language :: Python :: 3 :: Only
Classifier: Programming Language :: Python :: Implementation :: CPython
Classifier: Programming Language :: Python :: Implementation :: PyPy
Classifier: Topic :: Software Development :: Libraries :: Python Modules
Classifier: Topic :: Software Development :: Testing
Requires: sphinx
Requires: wrapt
Requires: PyYAML
Requires: argh
Requires: pathtools
Requires: setuptools
Provides: fuzzing
Provides: gp_decorators
